{
    "name": "hello-world",
    "nodes": [
        {
            "name": "shipping",
            "type": "service"
        },
        {
            "name": "order_db",
            "type": "database"
        },
        {
            "name": "order",
            "type": "service"
        },
        {
            "name": "rabbitmq",
            "type": "communicationpattern",
            "ctype": "MessageBroker"
        },
        {
            "name": "gateway",
            "type": "communicationpattern",
            "ctype": "ApiGateway"
        },
        {
            "name": "DB manager",
            "type": "service"
        }
    ],
    "links": [
        {
            "source": "shipping",
            "target": "DB manager",
            "timeout": false,
            "type": "runtime"
        },
        {
            "source": "shipping",
            "target": "rabbitmq",
            "timeout": false,
            "type": "runtime"
        },
        {
            "source": "order",
            "target": "shipping",
            "timeout": false,
            "type": "runtime"
        },
        {
            "source": "order",
            "target": "DB manager",
            "timeout": false,
            "type": "runtime"
        },
        {
            "source": "order",
            "target": "rabbitmq",
            "timeout": false,
            "type": "runtime"
        },
        {
            "source": "gateway",
            "target": "shipping",
            "timeout": false,
            "type": "runtime"
        },
        {
            "source": "DB manager",
            "target": "order_db",
            "timeout": false,
            "type": "runtime"
        }
    ],
    "groups": [
        {
            "name": "edgenodes",
            "type": "edgegroup",
            "members": [
                "shipping",
                "order",
                "gateway"
            ]
        },
        {
            "name": "team1",
            "type": "squadgroup",
            "members": [
                "shipping",
                "rabbitmq"
            ]
        },
        {
            "name": "team2",
            "type": "squadgroup",
            "members": [
                "order",
                "order_db",
                "DB manager"
            ]
        }
    ]
}